mdptoolbox/__init__.py
mdptoolbox/error.py
mdptoolbox/example.py
mdptoolbox/mdp.py
mdptoolbox/util.py
pymdptoolbox_roi-4.2.0.dist-info/licenses/LICENSE.txt
pymdptoolbox_roi-4.2.0.dist-info/METADATA
pymdptoolbox_roi-4.2.0.dist-info/WHEEL
pymdptoolbox_roi-4.2.0.dist-info/top_level.txt
pymdptoolbox_roi-4.2.0.dist-info/RECORD
